README.md
setup.py
efficientformers/version.py
efficientformers.egg-info/PKG-INFO
efficientformers.egg-info/SOURCES.txt
efficientformers.egg-info/dependency_links.txt
efficientformers.egg-info/entry_points.txt
efficientformers.egg-info/requires.txt
efficientformers.egg-info/top_level.txt
efficientformers/cv/ecoformer.py
efficientformers/cv/efficientformer.py