Metadata-Version: 2.1
Name: efficientformers
Version: 0.1.1
Summary: Collection of efficientformers
Home-page: https://github.com/jinfagang/efficientformers
Author: Lucas Jin
Author-email: jinfagang19@163.com
License: Apache 2.0
Keywords: deep learning,neural network,builder
Platform: any
